lab07/important files/receiver.v
module receiver #(
    parameter Baudrate  = 115200,
    parameter Clockrate = 50000000
)(
    input rst,
    input clk,
    input serial_in,
    output reg [6:0] data,
    output reg parity_bit,
    output reg [7:0] data_with_parity,
    output reg valid,
    output reg parity_error
);

    localparam integer CLKS_PER_BIT      = Clockrate / Baudrate;
    localparam integer CLKS_PER_HALF_BIT = CLKS_PER_BIT / 2;

    localparam IDLE   = 3'd0;
    localparam START  = 3'd1;
    localparam PARITY = 3'd2;
    localparam DATA   = 3'd3;
    localparam STOP   = 3'd4;

    reg [2:0] state;
    reg [31:0] delay;
    reg [2:0] bit_counter;
    reg [6:0] data_reg;
    reg parity_reg;

    always @(posedge clk or negedge rst) begin
        if (!rst) begin
            state            <= IDLE;
            delay            <= 0;
            bit_counter      <= 0;
            data             <= 0;
            data_reg         <= 0;
            parity_bit       <= 0;
            parity_reg       <= 0;
            data_with_parity <= 0;
            valid            <= 1'b0;
            parity_error     <= 1'b0;
        end else begin
            valid <= 1'b0;

            case (state)

                IDLE: begin
                    delay        <= 0;
                    bit_counter  <= 0;
                    parity_error <= 1'b0;

                    if (serial_in == 1'b0) begin
                        delay <= CLKS_PER_HALF_BIT - 1;
                        state <= START;
                    end
                end

                START: begin
                    if (delay == 0) begin
                        if (serial_in == 1'b0) begin
                            delay <= CLKS_PER_BIT - 1;
                            state <= PARITY;
                        end else begin
                            state <= IDLE;
                        end
                    end else begin
                        delay <= delay - 1;
                    end
                end

                PARITY: begin
                    if (delay == 0) begin
                        parity_reg <= serial_in;
                        parity_bit <= serial_in;
                        delay      <= CLKS_PER_BIT - 1;
                        state      <= DATA;
                    end else begin
                        delay <= delay - 1;
                    end
                end

                DATA: begin
                    if (delay == 0) begin
                        data_reg[bit_counter] <= serial_in;

                        if (bit_counter == 6) begin
                            delay <= CLKS_PER_BIT - 1;
                            state <= STOP;
                        end else begin
                            bit_counter <= bit_counter + 1;
                            delay       <= CLKS_PER_BIT - 1;
                        end
                    end else begin
                        delay <= delay - 1;
                    end
                end

                STOP: begin
                    if (delay == 0) begin
                        if (serial_in == 1'b1) begin
                            data <= data_reg;
                            data_with_parity <= {data_reg, parity_reg};

                            if ((^data_reg) == parity_reg) begin
                                parity_error <= 1'b0;
                            end else begin
                                parity_error <= 1'b1;
                            end

                            valid <= 1'b1;
                        end else begin
                            parity_error <= 1'b1;
                        end

                        state <= IDLE;
                    end else begin
                        delay <= delay - 1;
                    end
                end

                default: begin
                    state <= IDLE;
                end

            endcase
        end
    end

endmodule

lab07/important files/sender.v
module sender #(
    parameter Baudrate  = 115200,
    parameter Clockrate = 50000000
)(
    input rst,
    input clk,
    input start,
    input [6:0] data,
    output reg serial_out,
    output reg busy,
    output reg done
);

    localparam integer CLKS_PER_BIT = Clockrate / Baudrate;

    localparam IDLE   = 3'd0;
    localparam START  = 3'd1;
    localparam PARITY = 3'd2;
    localparam DATA   = 3'd3;
    localparam STOP   = 3'd4;

    reg [2:0] state;
    reg [31:0] delay;
    reg [2:0] bit_counter;
    reg [6:0] data_reg;
    reg parity_reg;

    always @(posedge clk or negedge rst) begin
        if (!rst) begin
            state       <= IDLE;
            delay       <= 0;
            bit_counter <= 0;
            data_reg    <= 0;
            parity_reg  <= 0;
            serial_out  <= 1'b1;
            busy        <= 1'b0;
            done        <= 1'b0;
        end else begin
            done <= 1'b0;

            case (state)

                IDLE: begin
                    serial_out  <= 1'b1;
                    busy        <= 1'b0;
                    delay       <= 0;
                    bit_counter <= 0;

                    if (start) begin
                        data_reg    <= data;
                        parity_reg  <= ^data;      // even parity
                        serial_out  <= 1'b0;       // start bit
                        busy        <= 1'b1;
                        delay       <= CLKS_PER_BIT - 1;
                        state       <= START;
                    end
                end

                START: begin
                    if (delay == 0) begin
                        serial_out <= parity_reg;   // parity bit
                        delay      <= CLKS_PER_BIT - 1;
                        state      <= PARITY;
                    end else begin
                        delay <= delay - 1;
                    end
                end

                PARITY: begin
                    if (delay == 0) begin
                        serial_out  <= data_reg[0]; // first data bit
                        bit_counter <= 0;
                        delay       <= CLKS_PER_BIT - 1;
                        state       <= DATA;
                    end else begin
                        delay <= delay - 1;
                    end
                end

                DATA: begin
                    if (delay == 0) begin
                        if (bit_counter == 6) begin
                            serial_out <= 1'b1;     // stop bit
                            delay      <= CLKS_PER_BIT - 1;
                            state      <= STOP;
                        end else begin
                            bit_counter <= bit_counter + 1;
                            serial_out  <= data_reg[bit_counter + 1];
                            delay       <= CLKS_PER_BIT - 1;
                        end
                    end else begin
                        delay <= delay - 1;
                    end
                end

                STOP: begin
                    if (delay == 0) begin
                        serial_out <= 1'b1;
                        busy       <= 1'b0;
                        done       <= 1'b1;
                        state      <= IDLE;
                    end else begin
                        delay <= delay - 1;
                    end
                end

                default: begin
                    state      <= IDLE;
                    serial_out <= 1'b1;
                    busy       <= 1'b0;
                    done       <= 1'b0;
                end

            endcase
        end
    end

endmodule

lab07/important files/uart.v
module uart #(
    parameter Baudrate  = 115200,
    parameter Clockrate = 50000000
)(
    input clk,
    input rst,

    input start,
    input [6:0] data_sender,

    input rx,
    output tx,

    output [6:0] data_receiver,
    output parity_receiver,
    output [7:0] data_with_parity,
    output valid,
    output parity_error,

    output tx_busy,
    output tx_done
);

    sender #(
        .Baudrate(Baudrate),
        .Clockrate(Clockrate)
    ) sender1 (
        .rst(rst),
        .clk(clk),
        .start(start),
        .data(data_sender),
        .serial_out(tx),
        .busy(tx_busy),
        .done(tx_done)
    );

    receiver #(
        .Baudrate(Baudrate),
        .Clockrate(Clockrate)
    ) receiver1 (
        .rst(rst),
        .clk(clk),
        .serial_in(rx),
        .data(data_receiver),
        .parity_bit(parity_receiver),
        .data_with_parity(data_with_parity),
        .valid(valid),
        .parity_error(parity_error)
    );

endmodule

lab07/important files/test_bench.v
`timescale 1ns/1ps

module test_bench;

    parameter Baudrate  = 4;
    parameter Clockrate = 16;

    reg clk;
    reg rst;

    reg start1;
    reg [6:0] data_sender1;

    wire tx1;
    wire rx2;

    wire [6:0] data_receiver2;
    wire parity_receiver2;
    wire [7:0] data_with_parity2;
    wire valid2;
    wire parity_error2;

    wire tx_busy1;
    wire tx_done1;

    assign rx2 = tx1;

    uart #(
        .Baudrate(Baudrate),
        .Clockrate(Clockrate)
    ) uart1 (
        .clk(clk),
        .rst(rst),

        .start(start1),
        .data_sender(data_sender1),

        .rx(1'b1),
        .tx(tx1),

        .data_receiver(),
        .parity_receiver(),
        .data_with_parity(),
        .valid(),
        .parity_error(),

        .tx_busy(tx_busy1),
        .tx_done(tx_done1)
    );

    uart #(
        .Baudrate(Baudrate),
        .Clockrate(Clockrate)
    ) uart2 (
        .clk(clk),
        .rst(rst),

        .start(1'b0),
        .data_sender(7'b0000000),

        .rx(rx2),
        .tx(),

        .data_receiver(data_receiver2),
        .parity_receiver(parity_receiver2),
        .data_with_parity(data_with_parity2),
        .valid(valid2),
        .parity_error(parity_error2),

        .tx_busy(),
        .tx_done()
    );

    initial begin
        clk = 1'b0;
        forever #1 clk = ~clk;
    end

    task send_and_check;
        input [6:0] test_data;
        begin
            @(posedge clk);
            data_sender1 <= test_data;
            start1 <= 1'b1;

            @(posedge clk);
            start1 <= 1'b0;

            wait(valid2 == 1'b1);
            @(posedge clk);

            if (parity_error2) begin
                $display("ERROR: Parity error detected for data = %b", test_data);
            end else if (data_receiver2 !== test_data) begin
                $display("ERROR: Sent = %b, Received = %b", test_data, data_receiver2);
            end else begin
                $display("PASS : Sent = %b, Received = %b, Parity = %b, Register8 = %b",
                         test_data, data_receiver2, parity_receiver2, data_with_parity2);
            end

            repeat(5) @(posedge clk);
        end
    endtask

    initial begin
        $dumpfile("uart_test.vcd");
        $dumpvars(0, test_bench);

        rst = 1'b0;
        start1 = 1'b0;
        data_sender1 = 7'b0000000;

        repeat(5) @(posedge clk);
        rst = 1'b1;

        repeat(5) @(posedge clk);

        send_and_check(7'b0000000);
        send_and_check(7'b1111111);
        send_and_check(7'b1010101);
        send_and_check(7'b1100101);
        send_and_check(7'b0010110);
        send_and_check(7'b1000010);
        send_and_check(7'b0000001);
        send_and_check(7'b1000000);

        repeat(20) @(posedge clk);

        $display("UART test finished.");
        $finish;
    end

endmodule

lab07/important files/uart_test.vcd
$date
	Sat Jun 06 02:00:04 2026
$end
$version
	ModelSim Version 10.5b
$end
$timescale
	1ps
$end

$scope module test_bench $end
$var parameter 32 ! Baudrate $end
$var parameter 32 " Clockrate $end
$var reg 1 # clk $end
$var reg 1 $ rst $end
$var reg 1 % start1 $end
$var reg 7 & data_sender1 [6:0] $end
$var wire 1 ' tx1 $end
$var wire 1 ( rx2 $end
$var wire 1 ) data_receiver2 [6] $end
$var wire 1 * data_receiver2 [5] $end
$var wire 1 + data_receiver2 [4] $end
$var wire 1 , data_receiver2 [3] $end
$var wire 1 - data_receiver2 [2] $end
$var wire 1 . data_receiver2 [1] $end
$var wire 1 / data_receiver2 [0] $end
$var wire 1 0 parity_receiver2 $end
$var wire 1 1 data_with_parity2 [7] $end
$var wire 1 2 data_with_parity2 [6] $end
$var wire 1 3 data_with_parity2 [5] $end
$var wire 1 4 data_with_parity2 [4] $end
$var wire 1 5 data_with_parity2 [3] $end
$var wire 1 6 data_with_parity2 [2] $end
$var wire 1 7 data_with_parity2 [1] $end
$var wire 1 8 data_with_parity2 [0] $end
$var wire 1 9 valid2 $end
$var wire 1 : parity_error2 $end
$var wire 1 ; tx_busy1 $end
$var wire 1 < tx_done1 $end

$scope task send_and_check $end
$var reg 7 = test_data [6:0] $end
$upscope $end

$scope module uart1 $end
$var parameter 32 > Baudrate $end
$var parameter 32 ? Clockrate $end
$var wire 1 @ clk $end
$var wire 1 A rst $end
$var wire 1 B start $end
$var wire 1 C data_sender [6] $end
$var wire 1 D data_sender [5] $end
$var wire 1 E data_sender [4] $end
$var wire 1 F data_sender [3] $end
$var wire 1 G data_sender [2] $end
$var wire 1 H data_sender [1] $end
$var wire 1 I data_sender [0] $end
$var wire 1 J rx $end
$var wire 1 ' tx $end
$var wire 1 K data_receiver [6] $end
$var wire 1 L data_receiver [5] $end
$var wire 1 M data_receiver [4] $end
$var wire 1 N data_receiver [3] $end
$var wire 1 O data_receiver [2] $end
$var wire 1 P data_receiver [1] $end
$var wire 1 Q data_receiver [0] $end
$var wire 1 R parity_receiver $end
$var wire 1 S data_with_parity [7] $end
$var wire 1 T data_with_parity [6] $end
$var wire 1 U data_with_parity [5] $end
$var wire 1 V data_with_parity [4] $end
$var wire 1 W data_with_parity [3] $end
$var wire 1 X data_with_parity [2] $end
$var wire 1 Y data_with_parity [1] $end
$var wire 1 Z data_with_parity [0] $end
$var wire 1 [ valid $end
$var wire 1 \ parity_error $end
$var wire 1 ; tx_busy $end
$var wire 1 < tx_done $end

$scope module sender1 $end
$var parameter 32 ] Baudrate $end
$var parameter 32 ^ Clockrate $end
$var parameter 32 _ CLKS_PER_BIT $end
$var parameter 3 ` IDLE $end
$var parameter 3 a START $end
$var parameter 3 b PARITY $end
$var parameter 3 c DATA $end
$var parameter 3 d STOP $end
$var wire 1 A rst $end
$var wire 1 @ clk $end
$var wire 1 B start $end
$var wire 1 C data [6] $end
$var wire 1 D data [5] $end
$var wire 1 E data [4] $end
$var wire 1 F data [3] $end
$var wire 1 G data [2] $end
$var wire 1 H data [1] $end
$var wire 1 I data [0] $end
$var reg 1 e serial_out $end
$var reg 1 f busy $end
$var reg 1 g done $end
$var reg 3 h state [2:0] $end
$var reg 32 i delay [31:0] $end
$var reg 3 j bit_counter [2:0] $end
$var reg 7 k data_reg [6:0] $end
$var reg 1 l parity_reg $end
$upscope $end

$scope module receiver1 $end
$var parameter 32 m Baudrate $end
$var parameter 32 n Clockrate $end
$var parameter 32 o CLKS_PER_BIT $end
$var parameter 32 p CLKS_PER_HALF_BIT $end
$var parameter 3 q IDLE $end
$var parameter 3 r START $end
$var parameter 3 s PARITY $end
$var parameter 3 t DATA $end
$var parameter 3 u STOP $end
$var wire 1 A rst $end
$var wire 1 @ clk $end
$var wire 1 J serial_in $end
$var reg 7 v data [6:0] $end
$var reg 1 w parity_bit $end
$var reg 8 x data_with_parity [7:0] $end
$var reg 1 y valid $end
$var reg 1 z parity_error $end
$var reg 3 { state [2:0] $end
$var reg 32 | delay [31:0] $end
$var reg 3 } bit_counter [2:0] $end
$var reg 7 ~ data_reg [6:0] $end
$var reg 1 !! parity_reg $end
$upscope $end
$upscope $end

$scope module uart2 $end
$var parameter 32 "! Baudrate $end
$var parameter 32 #! Clockrate $end
$var wire 1 $! clk $end
$var wire 1 %! rst $end
$var wire 1 &! start $end
$var wire 1 '! data_sender [6] $end
$var wire 1 (! data_sender [5] $end
$var wire 1 )! data_sender [4] $end
$var wire 1 *! data_sender [3] $end
$var wire 1 +! data_sender [2] $end
$var wire 1 ,! data_sender [1] $end
$var wire 1 -! data_sender [0] $end
$var wire 1 ( rx $end
$var wire 1 .! tx $end
$var wire 1 ) data_receiver [6] $end
$var wire 1 * data_receiver [5] $end
$var wire 1 + data_receiver [4] $end
$var wire 1 , data_receiver [3] $end
$var wire 1 - data_receiver [2] $end
$var wire 1 . data_receiver [1] $end
$var wire 1 / data_receiver [0] $end
$var wire 1 0 parity_receiver $end
$var wire 1 1 data_with_parity [7] $end
$var wire 1 2 data_with_parity [6] $end
$var wire 1 3 data_with_parity [5] $end
$var wire 1 4 data_with_parity [4] $end
$var wire 1 5 data_with_parity [3] $end
$var wire 1 6 data_with_parity [2] $end
$var wire 1 7 data_with_parity [1] $end
$var wire 1 8 data_with_parity [0] $end
$var wire 1 9 valid $end
$var wire 1 : parity_error $end
$var wire 1 /! tx_busy $end
$var wire 1 0! tx_done $end

$scope module sender1 $end
$var parameter 32 1! Baudrate $end
$var parameter 32 2! Clockrate $end
$var parameter 32 3! CLKS_PER_BIT $end
$var parameter 3 4! IDLE $end
$var parameter 3 5! START $end
$var parameter 3 6! PARITY $end
$var parameter 3 7! DATA $end
$var parameter 3 8! STOP $end
$var wire 1 %! rst $end
$var wire 1 $! clk $end
$var wire 1 &! start $end
$var wire 1 '! data [6] $end
$var wire 1 (! data [5] $end
$var wire 1 )! data [4] $end
$var wire 1 *! data [3] $end
$var wire 1 +! data [2] $end
$var wire 1 ,! data [1] $end
$var wire 1 -! data [0] $end
$var reg 1 9! serial_out $end
$var reg 1 :! busy $end
$var reg 1 ;! done $end
$var reg 3 <! state [2:0] $end
$var reg 32 =! delay [31:0] $end
$var reg 3 >! bit_counter [2:0] $end
$var reg 7 ?! data_reg [6:0] $end
$var reg 1 @! parity_reg $end
$upscope $end

$scope module receiver1 $end
$var parameter 32 A! Baudrate $end
$var parameter 32 B! Clockrate $end
$var parameter 32 C! CLKS_PER_BIT $end
$var parameter 32 D! CLKS_PER_HALF_BIT $end
$var parameter 3 E! IDLE $end
$var parameter 3 F! START $end
$var parameter 3 G! PARITY $end
$var parameter 3 H! DATA $end
$var parameter 3 I! STOP $end
$var wire 1 %! rst $end
$var wire 1 $! clk $end
$var wire 1 ( serial_in $end
$var reg 7 J! data [6:0] $end
$var reg 1 K! parity_bit $end
$var reg 8 L! data_with_parity [7:0] $end
$var reg 1 M! valid $end
$var reg 1 N! parity_error $end
$var reg 3 O! state [2:0] $end
$var reg 32 P! delay [31:0] $end
$var reg 3 Q! bit_counter [2:0] $end
$var reg 7 R! data_reg [6:0] $end
$var reg 1 S! parity_reg $end
$upscope $end
$upscope $end
$upscope $end
$enddefinitions $end
#0
$dumpvars
0#
0$
0%
b0 &
1e
0f
0g
b0 h
b0 i
b0 j
b0 k
0l
b0 v
0w
b0 x
0y
0z
b0 {
b0 |
b0 }
b0 ~
0!!
19!
0:!
0;!
b0 <!
b0 =!
b0 >!
b0 ?!
0@!
b0 J!
0K!
b0 L!
0M!
0N!
b0 O!
b0 P!
b0 Q!
b0 R!
0S!
bx =
b100 !
b10000 "
b100 >
b10000 ?
b100 ]
b10000 ^
b100 _
b0 `
b1 a
b10 b
b11 c
b100 d
b100 m
b10000 n
b100 o
b10 p
b0 q
b1 r
b10 s
b11 t
b100 u
b100 "!
b10000 #!
b100 1!
b10000 2!
b100 3!
b0 4!
b1 5!
b10 6!
b11 7!
b100 8!
b100 A!
b10000 B!
b100 C!
b10 D!
b0 E!
b1 F!
b10 G!
b11 H!
b100 I!
1'
1(
0/
0.
0-
0,
0+
0*
0)
00
08
07
06
05
04
03
02
01
09
0:
0;
0<
0-!
0,!
0+!
0*!
0)!
0(!
0'!
0&!
0%!
0$!
1J
0I
0H
0G
0F
0E
0D
0C
0B
0A
0@
0Q
0P
0O
0N
0M
0L
0K
0R
0Z
0Y
0X
0W
0V
0U
0T
0S
0[
0\
1.!
0/!
00!
$end
#1000
1#
1@
1$!
#2000
0#
0@
0$!
#3000
1#
1@
1$!
#4000
0#
0@
0$!
#5000
1#
1@
1$!
#6000
0#
0@
0$!
#7000
1#
1@
1$!
#8000
0#
0@
0$!
#9000
1#
1@
1$!
1$
1A
1%!
#10000
0#
0@
0$!
#11000
1#
1@
1$!
#12000
0#
0@
0$!
#13000
1#
1@
1$!
#14000
0#
0@
0$!
#15000
1#
1@
1$!
#16000
0#
0@
0$!
#17000
1#
1@
1$!
#18000
0#
0@
0$!
#19000
1#
1@
1$!
b0 =
#20000
0#
0@
0$!
#21000
1#
1@
1$!
1%
1B
#22000
0#
0@
0$!
#23000
1#
1@
1$!
0e
1f
b11 i
b1 h
0%
0'
1;
0B
0(
#24000
0#
0@
0$!
#25000
1#
1@
1$!
b1 P!
b1 O!
b10 i
#26000
0#
0@
0$!
#27000
1#
1@
1$!
b0 P!
b1 i
#28000
0#
0@
0$!
#29000
1#
1@
1$!
b11 P!
b10 O!
b0 i
#30000
0#
0@
0$!
#31000
1#
1@
1$!
b10 P!
b11 i
b10 h
#32000
0#
0@
0$!
#33000
1#
1@
1$!
b1 P!
b10 i
#34000
0#
0@
0$!
#35000
1#
1@
1$!
b0 P!
b1 i
#36000
0#
0@
0$!
#37000
1#
1@
1$!
b11 P!
b11 O!
b0 i
#38000
0#
0@
0$!
#39000
1#
1@
1$!
b10 P!
b11 i
b11 h
#40000
0#
0@
0$!
#41000
1#
1@
1$!
b1 P!
b10 i
#42000
0#
0@
0$!
#43000
1#
1@
1$!
b0 P!
b1 i
#44000
0#
0@
0$!
#45000
1#
1@
1$!
b1 Q!
b11 P!
b0 i
#46000
0#
0@
0$!
#47000
1#
1@
1$!
b10 P!
b1 j
b11 i
#48000
0#
0@
0$!
#49000
1#
1@
1$!
b1 P!
b10 i
#50000
0#
0@
0$!
#51000
1#
1@
1$!
b0 P!
b1 i
#52000
0#
0@
0$!
#53000
1#
1@
1$!
b10 Q!
b11 P!
b0 i
#54000
0#
0@
0$!
#55000
1#
1@
1$!
b10 P!
b10 j
b11 i
#56000
0#
0@
0$!
#57000
1#
1@
1$!
b1 P!
b10 i
#58000
0#
0@
0$!
#59000
1#
1@
1$!
b0 P!
b1 i
#60000
0#
0@
0$!
#61000
1#
1@
1$!
b11 Q!
b11 P!
b0 i
#62000
0#
0@
0$!
#63000
1#
1@
1$!
b10 P!
b11 j
b11 i
#64000
0#
0@
0$!
#65000
1#
1@
1$!
b1 P!
b10 i
#66000
0#
0@
0$!
#67000
1#
1@
1$!
b0 P!
b1 i
#68000
0#
0@
0$!
#69000
1#
1@
1$!
b100 Q!
b11 P!
b0 i
#70000
0#
0@
0$!
#71000
1#
1@
1$!
b10 P!
b100 j
b11 i
#72000
0#
0@
0$!
#73000
1#
1@
1$!
b1 P!
b10 i
#74000
0#
0@
0$!
#75000
1#
1@
1$!
b0 P!
b1 i
#76000
0#
0@
0$!
#77000
1#
1@
1$!
b101 Q!
b11 P!
b0 i
#78000
0#
0@
0$!
#79000
1#
1@
1$!
b10 P!
b101 j
b11 i
#80000
0#
0@
0$!
#81000
1#
1@
1$!
b1 P!
b10 i
#82000
0#
0@
0$!
#83000
1#
1@
1$!
b0 P!
b1 i
#84000
0#
0@
0$!
#85000
1#
1@
1$!
b110 Q!
b11 P!
b0 i
#86000
0#
0@
0$!
#87000
1#
1@
1$!
b10 P!
b110 j
b11 i
#88000
0#
0@
0$!
#89000
1#
1@
1$!
b1 P!
b10 i
#90000
0#
0@
0$!
#91000
1#
1@
1$!
b0 P!
b1 i
#92000
0#
0@
0$!
#93000
1#
1@
1$!
b11 P!
b100 O!
b0 i
#94000
0#
0@
0$!
#95000
1#
1@
1$!
b10 P!
1e
b11 i
b100 h
1'
1(
#96000
0#
0@
0$!
#97000
1#
1@
1$!
b1 P!
b10 i
#98000
0#
0@
0$!
#99000
1#
1@
1$!
b0 P!
b1 i
#100000
0#
0@
0$!
#101000
1#
1@
1$!
1M!
b0 O!
b0 i
19
#102000
0#
0@
0$!
#103000
1#
1@
1$!
0M!
b0 Q!
0f
1g
b0 h
09
0;
1<
#104000
0#
0@
0$!
#105000
1#
1@
1$!
0g
b0 j
0<
#106000
0#
0@
0$!
#107000
1#
1@
1$!
#108000
0#
0@
0$!
#109000
1#
1@
1$!
#110000
0#
0@
0$!
#111000
1#
1@
1$!
#112000
0#
0@
0$!
#113000
1#
1@
1$!
b1111111 =
#114000
0#
0@
0$!
#115000
1#
1@
1$!
b1111111 &
1%
1I
1H
1G
1F
1E
1D
1C
1B
#116000
0#
0@
0$!
#117000
1#
1@
1$!
b1111111 k
1l
0e
1f
b11 i
b1 h
0%
0'
1;
0B
0(
#118000
0#
0@
0$!
#119000
1#
1@
1$!
b1 P!
b1 O!
b10 i
#120000
0#
0@
0$!
#121000
1#
1@
1$!
b0 P!
b1 i
#122000
0#
0@
0$!
#123000
1#
1@
1$!
b11 P!
b10 O!
b0 i
#124000
0#
0@
0$!
#125000
1#
1@
1$!
b10 P!
1e
b11 i
b10 h
1'
1(
#126000
0#
0@
0$!
#127000
1#
1@
1$!
b1 P!
b10 i
#128000
0#
0@
0$!
#129000
1#
1@
1$!
b0 P!
b1 i
#130000
0#
0@
0$!
#131000
1#
1@
1$!
1S!
1K!
b11 P!
b11 O!
b0 i
10
#132000
0#
0@
0$!
#133000
1#
1@
1$!
b10 P!
b11 i
b11 h
#134000
0#
0@
0$!
#135000
1#
1@
1$!
b1 P!
b10 i
#136000
0#
0@
0$!
#137000
1#
1@
1$!
b0 P!
b1 i
#138000
0#
0@
0$!
#139000
1#
1@
1$!
b1 R!
b1 Q!
b11 P!
b0 i
#140000
0#
0@
0$!
#141000
1#
1@
1$!
b10 P!
b1 j
b11 i
#142000
0#
0@
0$!
#143000
1#
1@
1$!
b1 P!
b10 i
#144000
0#
0@
0$!
#145000
1#
1@
1$!
b0 P!
b1 i
#146000
0#
0@
0$!
#147000
1#
1@
1$!
b11 R!
b10 Q!
b11 P!
b0 i
#148000
0#
0@
0$!
#149000
1#
1@
1$!
b10 P!
b10 j
b11 i
#150000
0#
0@
0$!
#151000
1#
1@
1$!
b1 P!
b10 i
#152000
0#
0@
0$!
#153000
1#
1@
1$!
b0 P!
b1 i
#154000
0#
0@
0$!
#155000
1#
1@
1$!
b111 R!
b11 Q!
b11 P!
b0 i
#156000
0#
0@
0$!
#157000
1#
1@
1$!
b10 P!
b11 j
b11 i
#158000
0#
0@
0$!
#159000
1#
1@
1$!
b1 P!
b10 i
#160000
0#
0@
0$!
#161000
1#
1@
1$!
b0 P!
b1 i
#162000
0#
0@
0$!
#163000
1#
1@
1$!
b1111 R!
b100 Q!
b11 P!
b0 i
#164000
0#
0@
0$!
#165000
1#
1@
1$!
b10 P!
b100 j
b11 i
#166000
0#
0@
0$!
#167000
1#
1@
1$!
b1 P!
b10 i
#168000
0#
0@
0$!
#169000
1#
1@
1$!
b0 P!
b1 i
#170000
0#
0@
0$!
#171000
1#
1@
1$!
b11111 R!
b101 Q!
b11 P!
b0 i
#172000
0#
0@
0$!
#173000
1#
1@
1$!
b10 P!
b101 j
b11 i
#174000
0#
0@
0$!
#175000
1#
1@
1$!
b1 P!
b10 i
#176000
0#
0@
0$!
#177000
1#
1@
1$!
b0 P!
b1 i
#178000
0#
0@
0$!
#179000
1#
1@
1$!
b111111 R!
b110 Q!
b11 P!
b0 i
#180000
0#
0@
0$!
#181000
1#
1@
1$!
b10 P!
b110 j
b11 i
#182000
0#
0@
0$!
#183000
1#
1@
1$!
b1 P!
b10 i
#184000
0#
0@
0$!
#185000
1#
1@
1$!
b0 P!
b1 i
#186000
0#
0@
0$!
#187000
1#
1@
1$!
b1111111 R!
b11 P!
b100 O!
b0 i
#188000
0#
0@
0$!
#189000
1#
1@
1$!
b10 P!
b11 i
b100 h
#190000
0#
0@
0$!
#191000
1#
1@
1$!
b1 P!
b10 i
#192000
0#
0@
0$!
#193000
1#
1@
1$!
b0 P!
b1 i
#194000
0#
0@
0$!
#195000
1#
1@
1$!
b1111111 J!
b11111111 L!
1M!
b0 O!
b0 i
18
17
16
15
14
13
12
11
1/
1.
1-
1,
1+
1*
1)
19
#196000
0#
0@
0$!
#197000
1#
1@
1$!
0M!
b0 Q!
0f
1g
b0 h
09
0;
1<
#198000
0#
0@
0$!
#199000
1#
1@
1$!
0g
b0 j
0<
#200000
0#
0@
0$!
#201000
1#
1@
1$!
#202000
0#
0@
0$!
#203000
1#
1@
1$!
#204000
0#
0@
0$!
#205000
1#
1@
1$!
#206000
0#
0@
0$!
#207000
1#
1@
1$!
b1010101 =
#208000
0#
0@
0$!
#209000
1#
1@
1$!
b1010101 &
1%
0H
0F
0D
1B
#210000
0#
0@
0$!
#211000
1#
1@
1$!
b1010101 k
0l
0e
1f
b11 i
b1 h
0%
0'
1;
0B
0(
#212000
0#
0@
0$!
#213000
1#
1@
1$!
b1 P!
b1 O!
b10 i
#214000
0#
0@
0$!
#215000
1#
1@
1$!
b0 P!
b1 i
#216000
0#
0@
0$!
#217000
1#
1@
1$!
b11 P!
b10 O!
b0 i
#218000
0#
0@
0$!
#219000
1#
1@
1$!
b10 P!
b11 i
b10 h
#220000
0#
0@
0$!
#221000
1#
1@
1$!
b1 P!
b10 i
#222000
0#
0@
0$!
#223000
1#
1@
1$!
b0 P!
b1 i
#224000
0#
0@
0$!
#225000
1#
1@
1$!
0S!
0K!
b11 P!
b11 O!
b0 i
00
#226000
0#
0@
0$!
#227000
1#
1@
1$!
b10 P!
1e
b11 i
b11 h
1'
1(
#228000
0#
0@
0$!
#229000
1#
1@
1$!
b1 P!
b10 i
#230000
0#
0@
0$!
#231000
1#
1@
1$!
b0 P!
b1 i
#232000
0#
0@
0$!
#233000
1#
1@
1$!
b1 Q!
b11 P!
b0 i
#234000
0#
0@
0$!
#235000
1#
1@
1$!
b10 P!
b1 j
0e
b11 i
0'
0(
#236000
0#
0@
0$!
#237000
1#
1@
1$!
b1 P!
b10 i
#238000
0#
0@
0$!
#239000
1#
1@
1$!
b0 P!
b1 i
#240000
0#
0@
0$!
#241000
1#
1@
1$!
b1111101 R!
b10 Q!
b11 P!
b0 i
#242000
0#
0@
0$!
#243000
1#
1@
1$!
b10 P!
b10 j
1e
b11 i
1'
1(
#244000
0#
0@
0$!
#245000
1#
1@
1$!
b1 P!
b10 i
#246000
0#
0@
0$!
#247000
1#
1@
1$!
b0 P!
b1 i
#248000
0#
0@
0$!
#249000
1#
1@
1$!
b11 Q!
b11 P!
b0 i
#250000
0#
0@
0$!
#251000
1#
1@
1$!
b10 P!
b11 j
0e
b11 i
0'
0(
#252000
0#
0@
0$!
#253000
1#
1@
1$!
b1 P!
b10 i
#254000
0#
0@
0$!
#255000
1#
1@
1$!
b0 P!
b1 i
#256000
0#
0@
0$!
#257000
1#
1@
1$!
b1110101 R!
b100 Q!
b11 P!
b0 i
#258000
0#
0@
0$!
#259000
1#
1@
1$!
b10 P!
b100 j
1e
b11 i
1'
1(
#260000
0#
0@
0$!
#261000
1#
1@
1$!
b1 P!
b10 i
#262000
0#
0@
0$!
#263000
1#
1@
1$!
b0 P!
b1 i
#264000
0#
0@
0$!
#265000
1#
1@
1$!
b101 Q!
b11 P!
b0 i
#266000
0#
0@
0$!
#267000
1#
1@
1$!
b10 P!
b101 j
0e
b11 i
0'
0(
#268000
0#
0@
0$!
#269000
1#
1@
1$!
b1 P!
b10 i
#270000
0#
0@
0$!
#271000
1#
1@
1$!
b0 P!
b1 i
#272000
0#
0@
0$!
#273000
1#
1@
1$!
b1010101 R!
b110 Q!
b11 P!
b0 i
#274000
0#
0@
0$!
#275000
1#
1@
1$!
b10 P!
b110 j
1e
b11 i
1'
1(
#276000
0#
0@
0$!
#277000
1#
1@
1$!
b1 P!
b10 i
#278000
0#
0@
0$!
#279000
1#
1@
1$!
b0 P!
b1 i
#280000
0#
0@
0$!
#281000
1#
1@
1$!
b11 P!
b100 O!
b0 i
#282000
0#
0@
0$!
#283000
1#
1@
1$!
b10 P!
b11 i
b100 h
#284000
0#
0@
0$!
#285000
1#
1@
1$!
b1 P!
b10 i
#286000
0#
0@
0$!
#287000
1#
1@
1$!
b0 P!
b1 i
#288000
0#
0@
0$!
#289000
1#
1@
1$!
b1010101 J!
b10101010 L!
1M!
b0 O!
b0 i
08
06
04
02
0.
0,
0*
19
#290000
0#
0@
0$!
#291000
1#
1@
1$!
0M!
b0 Q!
0f
1g
b0 h
09
0;
1<
#292000
0#
0@
0$!
#293000
1#
1@
1$!
0g
b0 j
0<
#294000
0#
0@
0$!
#295000
1#
1@
1$!
#296000
0#
0@
0$!
#297000
1#
1@
1$!
#298000
0#
0@
0$!
#299000
1#
1@
1$!
#300000
0#
0@
0$!
#301000
1#
1@
1$!
b1100101 =
#302000
0#
0@
0$!
#303000
1#
1@
1$!
b1100101 &
1%
0E
1D
1B
#304000
0#
0@
0$!
#305000
1#
1@
1$!
b1100101 k
0e
1f
b11 i
b1 h
0%
0'
1;
0B
0(
#306000
0#
0@
0$!
