lab06/important files/digital_control_top.v
`timescale 1ns/1ps

module digital_control_top #(
    parameter TEMP_WIDTH = 8
)(
    input  wire                          clk,
    input  wire                          rst_n,
    input  wire signed [TEMP_WIDTH-1:0]  temp_c,
    output reg                           heater_on,
    output reg                           cooler_on,
    output reg  [3:0]                    cooler_speed_rps,
    output wire [1:0]                    thermal_state_dbg,
    output wire [1:0]                    speed_state_dbg
);

    // Heater/Cooler ON-OFF FSM states
    localparam [1:0] TH_IDLE = 2'd0;  // S1: Heater OFF, Cooler OFF
    localparam [1:0] TH_COOL = 2'd1;  // S2: Heater OFF, Cooler ON
    localparam [1:0] TH_HEAT = 2'd2;  // S3: Heater ON,  Cooler OFF

    // Cooler Rotational Speed FSM states
    localparam [1:0] CRS_OUT = 2'd0;  // OUT: cooler stopped, 0 RPS
    localparam [1:0] CRS_4   = 2'd1;  // S1: 4 RPS
    localparam [1:0] CRS_6   = 2'd2;  // S2: 6 RPS
    localparam [1:0] CRS_8   = 2'd3;  // S3: 8 RPS

    reg [1:0] thermal_state, thermal_next;
    reg [1:0] speed_state,   speed_next;

    assign thermal_state_dbg = thermal_state;
    assign speed_state_dbg   = speed_state;



    always @(posedge clk or negedge rst_n) begin
        if (!rst_n) begin
            thermal_state <= TH_IDLE;
            speed_state   <= CRS_OUT;
        end else begin
            thermal_state <= thermal_next;
            speed_state   <= speed_next;
        end
    end


    always @(*) begin
        thermal_next = thermal_state;

        case (thermal_state)
            TH_IDLE: begin
                if (temp_c > 8'sd35) begin
                    thermal_next = TH_COOL;
                end else if (temp_c < 8'sd15) begin
                    thermal_next = TH_HEAT;
                end
            end

            TH_COOL: begin
                if (temp_c < 8'sd25) begin
                    thermal_next = TH_IDLE;
                end
            end

            TH_HEAT: begin
                if (temp_c > 8'sd30) begin
                    thermal_next = TH_IDLE;
                end
            end

            default: begin

                thermal_next = TH_IDLE;
            end
        endcase
    end


    always @(*) begin
        if (thermal_next != TH_COOL) begin
            speed_next = CRS_OUT;
        end else begin
            speed_next = speed_state;

            case (speed_state)
                CRS_OUT: begin
                    if (temp_c > 8'sd35) begin
                        speed_next = CRS_4;
                    end
                end

                CRS_4: begin
                    if (temp_c < 8'sd25) begin
                        speed_next = CRS_OUT;
                    end else if (temp_c > 8'sd40) begin
                        speed_next = CRS_6;
                    end
                end

                CRS_6: begin
                    if (temp_c < 8'sd35) begin
                        speed_next = CRS_4;
                    end else if (temp_c > 8'sd45) begin
                        speed_next = CRS_8;
                    end
                end

                CRS_8: begin
                    if (temp_c < 8'sd40) begin
                        speed_next = CRS_6;
                    end
                end

                default: begin

                    speed_next = CRS_OUT;
                end
            endcase
        end
    end




    always @(*) begin

        heater_on        = 1'b0;
        cooler_on        = 1'b0;
        cooler_speed_rps = 4'd0;

        case (thermal_state)
            TH_IDLE: begin
                heater_on = 1'b0;
                cooler_on = 1'b0;
            end

            TH_COOL: begin
                heater_on = 1'b0;
                cooler_on = 1'b1;
            end

            TH_HEAT: begin
                heater_on = 1'b1;
                cooler_on = 1'b0;
            end

            default: begin
                heater_on = 1'b0;
                cooler_on = 1'b0;
            end
        endcase

        case (speed_state)
            CRS_OUT: cooler_speed_rps = 4'd0;
            CRS_4:   cooler_speed_rps = 4'd4;
            CRS_6:   cooler_speed_rps = 4'd6;
            CRS_8:   cooler_speed_rps = 4'd8;
            default: cooler_speed_rps = 4'd0;
        endcase
    end

endmodule

lab06/important files/tb_digital_control.v
`timescale 1ns/1ps

module tb_digital_control;

    localparam TEMP_WIDTH = 8;
    localparam CLK_PERIOD = 10;

    // Heater/Cooler states, matched with DUT encoding
    localparam [1:0] TH_IDLE = 2'd0;
    localparam [1:0] TH_COOL = 2'd1;
    localparam [1:0] TH_HEAT = 2'd2;
    localparam [1:0] TH_BAD  = 2'd3;

    // Cooler speed states, matched with DUT encoding
    localparam [1:0] CRS_OUT = 2'd0;
    localparam [1:0] CRS_4   = 2'd1;
    localparam [1:0] CRS_6   = 2'd2;
    localparam [1:0] CRS_8   = 2'd3;

    reg clk;
    reg rst_n;
    reg signed [TEMP_WIDTH-1:0] temp_c;

    wire heater_on;
    wire cooler_on;
    wire [3:0] cooler_speed_rps;
    wire [1:0] thermal_state_dbg;
    wire [1:0] speed_state_dbg;

    integer errors;
    integer tests;
    integer ts;
    integer ss;
    integer t;

    digital_control_top #(
        .TEMP_WIDTH(TEMP_WIDTH)
    ) dut (
        .clk(clk),
        .rst_n(rst_n),
        .temp_c(temp_c),
        .heater_on(heater_on),
        .cooler_on(cooler_on),
        .cooler_speed_rps(cooler_speed_rps),
        .thermal_state_dbg(thermal_state_dbg),
        .speed_state_dbg(speed_state_dbg)
    );

    initial begin
        clk = 1'b0;
        forever #(CLK_PERIOD/2) clk = ~clk;
    end

    function [1:0] exp_thermal_next;
        input [1:0] state;
        input signed [TEMP_WIDTH-1:0] temp;
        begin
            exp_thermal_next = state;
            case (state)
                TH_IDLE: begin
                    if (temp > 8'sd35) begin
                        exp_thermal_next = TH_COOL;
                    end else if (temp < 8'sd15) begin
                        exp_thermal_next = TH_HEAT;
                    end
                end

                TH_COOL: begin
                    if (temp < 8'sd25) begin
                        exp_thermal_next = TH_IDLE;
                    end
                end

                TH_HEAT: begin
                    if (temp > 8'sd30) begin
                        exp_thermal_next = TH_IDLE;
                    end
                end

                default: begin
                    exp_thermal_next = TH_IDLE;
                end
            endcase
        end
    endfunction

    function [1:0] exp_speed_next;
        input [1:0] th_state;
        input [1:0] sp_state;
        input signed [TEMP_WIDTH-1:0] temp;
        reg [1:0] th_next;
        begin
            th_next = exp_thermal_next(th_state, temp);

            if (th_next != TH_COOL) begin
                exp_speed_next = CRS_OUT;
            end else begin
                exp_speed_next = sp_state;
                case (sp_state)
                    CRS_OUT: begin
                        if (temp > 8'sd35) begin
                            exp_speed_next = CRS_4;
                        end
                    end

                    CRS_4: begin
                        if (temp < 8'sd25) begin
                            exp_speed_next = CRS_OUT;
                        end else if (temp > 8'sd40) begin
                            exp_speed_next = CRS_6;
                        end
                    end

                    CRS_6: begin
                        if (temp < 8'sd35) begin
                            exp_speed_next = CRS_4;
                        end else if (temp > 8'sd45) begin
                            exp_speed_next = CRS_8;
                        end
                    end

                    CRS_8: begin
                        if (temp < 8'sd40) begin
                            exp_speed_next = CRS_6;
                        end
                    end

                    default: begin
                        exp_speed_next = CRS_OUT;
                    end
                endcase
            end
        end
    endfunction

    function exp_heater;
        input [1:0] th_state;
        begin
            exp_heater = (th_state == TH_HEAT);
        end
    endfunction

    function exp_cooler;
        input [1:0] th_state;
        begin
            exp_cooler = (th_state == TH_COOL);
        end
    endfunction

    function [3:0] exp_speed_rps;
        input [1:0] th_state;
        input [1:0] sp_state;
        begin
            if (th_state != TH_COOL) begin
                exp_speed_rps = 4'd0;
            end else begin
                case (sp_state)
                    CRS_OUT: exp_speed_rps = 4'd0;
                    CRS_4:   exp_speed_rps = 4'd4;
                    CRS_6:   exp_speed_rps = 4'd6;
                    CRS_8:   exp_speed_rps = 4'd8;
                    default: exp_speed_rps = 4'd0;
                endcase
            end
        end
    endfunction

    task apply_reset;
        begin
            @(negedge clk);
            rst_n  = 1'b0;
            temp_c = 8'sd20;
            repeat (2) @(posedge clk);
            #1;
            check_state_and_outputs(TH_IDLE, CRS_OUT, "reset must put both FSMs in safe idle state");
            @(negedge clk);
            rst_n = 1'b1;
        end
    endtask

    task step_temp_and_check;
        input signed [TEMP_WIDTH-1:0] new_temp;
        input [1:0] exp_th;
        input [1:0] exp_sp;
        input [8*80-1:0] msg;
        begin
            @(negedge clk);
            temp_c = new_temp;
            @(posedge clk);
            #1;
            check_state_and_outputs(exp_th, exp_sp, msg);
        end
    endtask

    task check_state_and_outputs;
        input [1:0] exp_th;
        input [1:0] exp_sp;
        input [8*80-1:0] msg;
        begin
            tests = tests + 1;
            if (thermal_state_dbg !== exp_th ||
                speed_state_dbg   !== exp_sp ||
                heater_on         !== exp_heater(exp_th) ||
                cooler_on         !== exp_cooler(exp_th) ||
                cooler_speed_rps  !== exp_speed_rps(exp_th, exp_sp)) begin

                errors = errors + 1;
                $display("ERROR at time %0t | %0s", $time, msg);
                $display("  temp=%0d", temp_c);
                $display("  expected: thermal=%0d speed=%0d heater=%0b cooler=%0b rps=%0d",
                         exp_th, exp_sp, exp_heater(exp_th), exp_cooler(exp_th), exp_speed_rps(exp_th, exp_sp));
                $display("  observed: thermal=%0d speed=%0d heater=%0b cooler=%0b rps=%0d",
                         thermal_state_dbg, speed_state_dbg, heater_on, cooler_on, cooler_speed_rps);
            end
        end
    endtask

    task forced_transition_check;
        input [1:0] init_th;
        input [1:0] init_sp;
        input signed [TEMP_WIDTH-1:0] new_temp;
        reg [1:0] e_th;
        reg [1:0] e_sp;
        begin
            @(negedge clk);
            rst_n  = 1'b1;
            temp_c = new_temp;
            force dut.thermal_state = init_th;
            force dut.speed_state   = init_sp;
            #1;

            e_th = exp_thermal_next(init_th, new_temp);
            e_sp = exp_speed_next(init_th, init_sp, new_temp);

            release dut.thermal_state;
            release dut.speed_state;
            @(posedge clk);
            #1;

            tests = tests + 1;
            if (thermal_state_dbg !== e_th || speed_state_dbg !== e_sp ||
                heater_on !== exp_heater(e_th) || cooler_on !== exp_cooler(e_th) ||
                cooler_speed_rps !== exp_speed_rps(e_th, e_sp)) begin
                errors = errors + 1;
                $display("ERROR at time %0t | exhaustive transition mismatch", $time);
                $display("  init thermal=%0d init speed=%0d temp=%0d", init_th, init_sp, new_temp);
                $display("  expected next thermal=%0d next speed=%0d heater=%0b cooler=%0b rps=%0d",
                         e_th, e_sp, exp_heater(e_th), exp_cooler(e_th), exp_speed_rps(e_th, e_sp));
                $display("  observed next thermal=%0d next speed=%0d heater=%0b cooler=%0b rps=%0d",
                         thermal_state_dbg, speed_state_dbg, heater_on, cooler_on, cooler_speed_rps);
            end
        end
    endtask

    task run_reset_test;
        begin
            $display("TEST 1: reset behavior");
            apply_reset();
        end
    endtask

    task run_directed_thermal_sequence;
        begin
            $display("TEST 2: directed heater/cooler ON-OFF sequence");
            apply_reset();
            step_temp_and_check(8'sd36, TH_COOL, CRS_4,   "36C: idle -> cooler ON and CRS=4");
            step_temp_and_check(8'sd34, TH_COOL, CRS_4,   "34C: cooler state is held by hysteresis");
            step_temp_and_check(8'sd24, TH_IDLE, CRS_OUT, "24C: cooler turns OFF, CRS -> OUT");
            step_temp_and_check(8'sd14, TH_HEAT, CRS_OUT, "14C: heater turns ON");
            step_temp_and_check(8'sd20, TH_HEAT, CRS_OUT, "20C: heater state is held by hysteresis");
            step_temp_and_check(8'sd31, TH_IDLE, CRS_OUT, "31C: heater turns OFF");
        end
    endtask

    task run_directed_speed_sequence;
        begin
            $display("TEST 3: directed cooler speed increase/decrease sequence");
            apply_reset();
            step_temp_and_check(8'sd36, TH_COOL, CRS_4,   "36C: OUT -> 4 RPS");
            step_temp_and_check(8'sd41, TH_COOL, CRS_6,   "41C: 4 RPS -> 6 RPS");
            step_temp_and_check(8'sd44, TH_COOL, CRS_6,   "44C: 6 RPS is held below 46C");
            step_temp_and_check(8'sd46, TH_COOL, CRS_8,   "46C: 6 RPS -> 8 RPS");
            step_temp_and_check(8'sd44, TH_COOL, CRS_8,   "44C: 8 RPS is held until T < 40C");
            step_temp_and_check(8'sd39, TH_COOL, CRS_6,   "39C: 8 RPS -> 6 RPS");
            step_temp_and_check(8'sd34, TH_COOL, CRS_4,   "34C: 6 RPS -> 4 RPS");
            step_temp_and_check(8'sd24, TH_IDLE, CRS_OUT, "24C: 4 RPS -> OUT");
        end
    endtask

    task run_boundary_tests;
        begin
            $display("TEST 4: exact boundary values; all thresholds are strict");

            // Thermal boundaries
            forced_transition_check(TH_IDLE, CRS_OUT, 8'sd15); // not below 15
            forced_transition_check(TH_IDLE, CRS_OUT, 8'sd35); // not above 35
            forced_transition_check(TH_IDLE, CRS_OUT, 8'sd14); // below 15
            forced_transition_check(TH_IDLE, CRS_OUT, 8'sd36); // above 35

            forced_transition_check(TH_COOL, CRS_4, 8'sd25);   // not below 25
            forced_transition_check(TH_COOL, CRS_4, 8'sd24);   // below 25
            forced_transition_check(TH_HEAT, CRS_OUT, 8'sd30); // not above 30
            forced_transition_check(TH_HEAT, CRS_OUT, 8'sd31); // above 30

            // Speed boundaries while cooling is active
            forced_transition_check(TH_COOL, CRS_OUT, 8'sd35); // OUT holds at 35
            forced_transition_check(TH_COOL, CRS_OUT, 8'sd36); // OUT -> 4 at 36
            forced_transition_check(TH_COOL, CRS_4,   8'sd25); // 4 holds at 25
            forced_transition_check(TH_COOL, CRS_4,   8'sd40); // 4 holds at 40
            forced_transition_check(TH_COOL, CRS_4,   8'sd41); // 4 -> 6 at 41
            forced_transition_check(TH_COOL, CRS_6,   8'sd35); // 6 holds at 35
            forced_transition_check(TH_COOL, CRS_6,   8'sd45); // 6 holds at 45
            forced_transition_check(TH_COOL, CRS_6,   8'sd46); // 6 -> 8 at 46
            forced_transition_check(TH_COOL, CRS_8,   8'sd40); // 8 holds at 40
            forced_transition_check(TH_COOL, CRS_8,   8'sd39); // 8 -> 6 at 39

            // When cooling is not active, speed FSM must go/stay OUT
            forced_transition_check(TH_IDLE, CRS_4,   8'sd36);
            forced_transition_check(TH_HEAT, CRS_6,   8'sd39);
            forced_transition_check(TH_HEAT, CRS_8,   8'sd10);
        end
    endtask

    task run_exhaustive_transition_tests;
        begin
            $display("TEST 5: exhaustive legal transition coverage in valid sensor range (-10C to 60C)");
            for (ts = 0; ts < 3; ts = ts + 1) begin
                for (ss = 0; ss < 4; ss = ss + 1) begin
                    for (t = -10; t <= 60; t = t + 1) begin
                        forced_transition_check(ts[1:0], ss[1:0], t[7:0]);
                    end
                end
            end
            $display("  Checked 3*4*71 = 852 legal-state/temperature transitions.");
        end
    endtask

    task run_illegal_state_recovery_test;
        begin
            $display("TEST 6: safe recovery from illegal thermal state encoding");
            forced_transition_check(TH_BAD, CRS_OUT, 8'sd20);
        end
    endtask

    initial begin
        $dumpfile("digital_control_tb.vcd");
        $dumpvars(0, tb_digital_control);

        errors = 0;
        tests  = 0;
        rst_n  = 1'b1;
        temp_c = 8'sd20;

        run_reset_test();
        run_directed_thermal_sequence();
        run_directed_speed_sequence();
        run_boundary_tests();
        run_exhaustive_transition_tests();
        run_illegal_state_recovery_test();

        if (errors == 0) begin
            $display("------------------------------------------------------------");
            $display("PASS: all %0d checks completed without error.", tests);
            $display("------------------------------------------------------------");
        end else begin
            $display("------------------------------------------------------------");
            $display("FAIL: %0d errors detected in %0d checks.", errors, tests);
            $display("------------------------------------------------------------");
        end

        $finish;
    end

endmodule

lab06/important files/digital_control_tb.vcd
$date
	Mon Jun 01 07:46:38 2026
$end
$version
	ModelSim Version 10.5b
$end
$timescale
	1ps
$end

$scope module tb_digital_control $end
$var parameter 32 ! TEMP_WIDTH $end
$var parameter 32 " CLK_PERIOD $end
$var parameter 2 # TH_IDLE $end
$var parameter 2 $ TH_COOL $end
$var parameter 2 % TH_HEAT $end
$var parameter 2 & TH_BAD $end
$var parameter 2 ' CRS_OUT $end
$var parameter 2 ( CRS_4 $end
$var parameter 2 ) CRS_6 $end
$var parameter 2 * CRS_8 $end
$var reg 1 + clk $end
$var reg 1 , rst_n $end
$var reg 8 - temp_c [7:0] $end
$var wire 1 . heater_on $end
$var wire 1 / cooler_on $end
$var wire 1 0 cooler_speed_rps [3] $end
$var wire 1 1 cooler_speed_rps [2] $end
$var wire 1 2 cooler_speed_rps [1] $end
$var wire 1 3 cooler_speed_rps [0] $end
$var wire 1 4 thermal_state_dbg [1] $end
$var wire 1 5 thermal_state_dbg [0] $end
$var wire 1 6 speed_state_dbg [1] $end
$var wire 1 7 speed_state_dbg [0] $end
$var integer 32 8 errors $end
$var integer 32 9 tests $end
$var integer 32 : ts $end
$var integer 32 ; ss $end
$var integer 32 < t $end

$scope function exp_thermal_next $end
$var reg 2 = exp_thermal_next [1:0] $end
$var reg 2 > state [1:0] $end
$var reg 8 ? temp [7:0] $end
$upscope $end

$scope function exp_speed_next $end
$var reg 2 @ exp_speed_next [1:0] $end
$var reg 2 A th_state [1:0] $end
$var reg 2 B sp_state [1:0] $end
$var reg 8 C temp [7:0] $end
$var reg 2 D th_next [1:0] $end
$upscope $end

$scope function exp_heater $end
$var reg 1 E exp_heater $end
$var reg 2 F th_state [1:0] $end
$upscope $end

$scope function exp_cooler $end
$var reg 1 G exp_cooler $end
$var reg 2 H th_state [1:0] $end
$upscope $end

$scope function exp_speed_rps $end
$var reg 4 I exp_speed_rps [3:0] $end
$var reg 2 J th_state [1:0] $end
$var reg 2 K sp_state [1:0] $end
$upscope $end

$scope task apply_reset $end
$upscope $end

$scope task step_temp_and_check $end
$var reg 8 L new_temp [7:0] $end
$var reg 2 M exp_th [1:0] $end
$var reg 2 N exp_sp [1:0] $end
$var reg 640 O msg [639:0] $end
$upscope $end

$scope task check_state_and_outputs $end
$var reg 2 P exp_th [1:0] $end
$var reg 2 Q exp_sp [1:0] $end
$var reg 640 R msg [639:0] $end
$upscope $end

$scope task forced_transition_check $end
$var reg 2 S init_th [1:0] $end
$var reg 2 T init_sp [1:0] $end
$var reg 8 U new_temp [7:0] $end
$var reg 2 V e_th [1:0] $end
$var reg 2 W e_sp [1:0] $end
$upscope $end

$scope task run_reset_test $end
$upscope $end

$scope task run_directed_thermal_sequence $end
$upscope $end

$scope task run_directed_speed_sequence $end
$upscope $end

$scope task run_boundary_tests $end
$upscope $end

$scope task run_exhaustive_transition_tests $end
$upscope $end

$scope task run_illegal_state_recovery_test $end
$upscope $end

$scope module dut $end
$var parameter 32 X TEMP_WIDTH $end
$var parameter 2 Y TH_IDLE $end
$var parameter 2 Z TH_COOL $end
$var parameter 2 [ TH_HEAT $end
$var parameter 2 \ CRS_OUT $end
$var parameter 2 ] CRS_4 $end
$var parameter 2 ^ CRS_6 $end
$var parameter 2 _ CRS_8 $end
$var wire 1 ` clk $end
$var wire 1 a rst_n $end
$var wire 1 b temp_c [7] $end
$var wire 1 c temp_c [6] $end
$var wire 1 d temp_c [5] $end
$var wire 1 e temp_c [4] $end
$var wire 1 f temp_c [3] $end
$var wire 1 g temp_c [2] $end
$var wire 1 h temp_c [1] $end
$var wire 1 i temp_c [0] $end
$var reg 1 j heater_on $end
$var reg 1 k cooler_on $end
$var reg 4 l cooler_speed_rps [3:0] $end
$var wire 1 4 thermal_state_dbg [1] $end
$var wire 1 5 thermal_state_dbg [0] $end
$var wire 1 6 speed_state_dbg [1] $end
$var wire 1 7 speed_state_dbg [0] $end
$var reg 2 m thermal_state [1:0] $end
$var reg 2 n thermal_next [1:0] $end
$var reg 2 o speed_state [1:0] $end
$var reg 2 p speed_next [1:0] $end
$upscope $end
$upscope $end
$enddefinitions $end
#0
$dumpvars
0+
1,
b10100 -
xj
xk
bx l
bx m
b0 n
bx o
b0 p
bx =
bx >
bx ?
bx @
bx A
bx B
bx C
bx D
xE
bx F
xG
bx H
bx I
bx J
bx K
bx L
bx M
bx N
bx O
bx P
bx Q
bx R
bx S
bx T
bx U
bx V
bx W
b1000 !
b1010 "
b0 #
b1 $
b10 %
b11 &
b0 '
b1 (
b10 )
b11 *
b1000 X
b0 Y
b1 Z
b10 [
b0 \
b1 ]
b10 ^
b11 _
b0 8
b0 9
bx :
bx ;
bx <
x.
x/
x3
x2
x1
x0
x5
x4
x7
x6
0i
0h
1g
0f
1e
0d
0c
0b
1a
0`
$end
#5000
1+
1`
b0 m
b0 o
07
06
05
04
0j
0k
b0 l
0.
0/
03
02
01
00
#10000
0+
0`
0,
0a
#15000
1+
1`
#20000
0+
0`
#25000
1+
1`
#26000
b0 P
b0 Q
b1110010011001010111001101100101011101000010000001101101011101010111001101110100001000000111000001110101011101000010000001100010011011110111010001101000001000000100011001010011010011010111001100100000011010010110111000100000011100110110000101100110011001010010000001101001011001000110110001100101001000000111001101110100011000010111010001100101 R
b1 9
b0 F
0E
b0 H
0G
b0 J
b0 K
b0 I
#30000
0+
0`
1,
1a
#35000
1+
1`
#40000
0+
0`
0,
0a
#45000
1+
1`
#50000
0+
0`
#55000
1+
1`
#56000
b10 9
#60000
0+
0`
1,
b100100 L
b1 M
b1 N
b11001100110110010000110011101000100000011010010110010001101100011001010010000000101101001111100010000001100011011011110110111101101100011001010111001000100000010011110100111000100000011000010110111001100100001000000100001101010010010100110011110100110100 O
1a
#65000
1+
1`
#70000
0+
0`
b100100 -
0e
1d
b1 n
b1 p
#75000
1+
1`
b1 m
b1 o
17
15
1k
b100 l
1/
11
#76000
b1 P
b1 Q
b11001100110110010000110011101000100000011010010110010001101100011001010010000000101101001111100010000001100011011011110110111101101100011001010111001000100000010011110100111000100000011000010110111001100100001000000100001101010010010100110011110100110100 R
b11 9
b1 F
b1 H
1G
b1 J
b1 K
b100 I
b100010 L
b1100110011010001000011001110100010000001100011011011110110111101101100011001010111001000100000011100110111010001100001011101000110010100100000011010010111001100100000011010000110010101101100011001000010000001100010011110010010000001101000011110010111001101110100011001010111001001100101011100110110100101110011 O
#80000
0+
0`
b100010 -
1h
0g
#85000
1+
1`
#86000
b1100110011010001000011001110100010000001100011011011110110111101101100011001010111001000100000011100110111010001100001011101000110010100100000011010010111001100100000011010000110010101101100011001000010000001100010011110010010000001101000011110010111001101110100011001010111001001100101011100110110100101110011 R
b100 9
b11000 L
b0 M
b0 N
b1100100011010001000011001110100010000001100011011011110110111101101100011001010111001000100000011101000111010101110010011011100111001100100000010011110100011001000110001011000010000001000011010100100101001100100000001011010011111000100000010011110101010101010100 O
#90000
0+
0`
b11000 -
0h
1f
1e
0d
b0 n
b0 p
#95000
1+
1`
b0 m
b0 o
07
05
0k
b0 l
0/
01
#96000
b0 P
b0 Q
b1100100011010001000011001110100010000001100011011011110110111101101100011001010111001000100000011101000111010101110010011011100111001100100000010011110100011001000110001011000010000001000011010100100101001100100000001011010011111000100000010011110101010101010100 R
b101 9
b0 F
b0 H
0G
b0 J
b0 K
b0 I
b1110 L
b10 M
b11000100110100010000110011101000100000011010000110010101100001011101000110010101110010001000000111010001110101011100100110111001110011001000000100111101001110 O
#100000
0+
0`
b1110 -
1h
1g
0e
b10 n
#105000
1+
1`
b10 m
14
1j
1.
#106000
b10 P
b11000100110100010000110011101000100000011010000110010101100001011101000110010101110010001000000111010001110101011100100110111001110011001000000100111101001110 R
b110 9
b10 F
1E
b10 H
b10 J
b10100 L
b1100100011000001000011001110100010000001101000011001010110000101110100011001010111001000100000011100110111010001100001011101000110010100100000011010010111001100100000011010000110010101101100011001000010000001100010011110010010000001101000011110010111001101110100011001010111001001100101011100110110100101110011 O
#110000
0+
0`
b10100 -
0h
0f
1e
#115000
1+
1`
#116000
b1100100011000001000011001110100010000001101000011001010110000101110100011001010111001000100000011100110111010001100001011101000110010100100000011010010111001100100000011010000110010101101100011001000010000001100010011110010010000001101000011110010111001101110100011001010111001001100101011100110110100101110011 R
b111 9
b11111 L
b0 M
b1100110011000101000011001110100010000001101000011001010110000101110100011001010111001000100000011101000111010101110010011011100111001100100000010011110100011001000110 O
#120000
0+
0`
b11111 -
1i
1h
1f
b0 n
#125000
1+
1`
b0 m
04
0j
0.
#126000
b0 P
b1100110011000101000011001110100010000001101000011001010110000101110100011001010111001000100000011101000111010101110010011011100111001100100000010011110100011001000110 R
b1000 9
b0 F
0E
b0 H
b0 J
#130000
0+
0`
0,
b10100 -
0a
0i
0h
0f
#135000
1+
1`
#140000
0+
0`
#145000
1+
1`
#146000
b1110010011001010111001101100101011101000010000001101101011101010111001101110100001000000111000001110101011101000010000001100010011011110111010001101000001000000100011001010011010011010111001100100000011010010110111000100000011100110110000101100110011001010010000001101001011001000110110001100101001000000111001101110100011000010111010001100101 R
b1001 9
#150000
0+
0`
1,
b100100 L
b1 M
b1 N
b11001100110110010000110011101000100000010011110101010101010100001000000010110100111110001000000011010000100000010100100101000001010011 O
1a
#155000
1+
1`
#160000
0+
0`
b100100 -
0e
1d
b1 n
b1 p
#165000
1+
1`
b1 m
b1 o
17
15
1k
b100 l
1/
11
#166000
b1 P
b1 Q
b11001100110110010000110011101000100000010011110101010101010100001000000010110100111110001000000011010000100000010100100101000001010011 R
b1010 9
b1 F
b1 H
1G
b1 J
b1 K
b100 I
b101001 L
b10 N
b110100001100010100001100111010001000000011010000100000010100100101000001010011001000000010110100111110001000000011011000100000010100100101000001010011 O
#170000
0+
0`
b101001 -
1i
0g
1f
b10 p
#175000
1+
1`
b10 o
07
16
0k
b0 l
1k
b110 l
12
#176000
b10 Q
b110100001100010100001100111010001000000011010000100000010100100101000001010011001000000010110100111110001000000011011000100000010100100101000001010011 R
b1011 9
b10 K
b110 I
b101100 L
b110100001101000100001100111010001000000011011000100000010100100101000001010011001000000110100101110011001000000110100001100101011011000110010000100000011000100110010101101100011011110111011100100000001101000011011001000011 O
#180000
0+
0`
b101100 -
0i
1g
#185000
1+
1`
#186000
b110100001101000100001100111010001000000011011000100000010100100101000001010011001000000110100101110011001000000110100001100101011011000110010000100000011000100110010101101100011011110111011100100000001101000011011001000011 R
b1100 9
b101110 L
b11 N
b110100001101100100001100111010001000000011011000100000010100100101000001010011001000000010110100111110001000000011100000100000010100100101000001010011 O
#190000
0+
0`
b101110 -
1h
b11 p
#195000
1+
1`
b11 o
17
0k
b0 l
1k
b1000 l
02
01
10
#196000
b11 Q
b110100001101100100001100111010001000000011011000100000010100100101000001010011001000000010110100111110001000000011100000100000010100100101000001010011 R
b1101 9
b11 K
b1000 I
b101100 L
b11010000110100010000110011101000100000001110000010000001010010010100000101001100100000011010010111001100100000011010000110010101101100011001000010000001110101011011100111010001101001011011000010000001010100001000000011110000100000001101000011000001000011 O
#200000
0+
0`
b101100 -
0h
#205000
1+
1`
#206000
b11010000110100010000110011101000100000001110000010000001010010010100000101001100100000011010010111001100100000011010000110010101101100011001000010000001110101011011100111010001101001011011000010000001010100001000000011110000100000001101000011000001000011 R
b1110 9
b100111 L
b10 N
b110011001110010100001100111010001000000011100000100000010100100101000001010011001000000010110100111110001000000011011000100000010100100101000001010011 O
#210000
0+
0`
b100111 -
1i
1h
0f
b10 p
#215000
1+
1`
b10 o
07
0k
b0 l
1k
b110 l
12
11
00
#216000
b10 Q
b110011001110010100001100111010001000000011100000100000010100100101000001010011001000000010110100111110001000000011011000100000010100100101000001010011 R
b1111 9
b10 K
b110 I
b100010 L
b1 N
b110011001101000100001100111010001000000011011000100000010100100101000001010011001000000010110100111110001000000011010000100000010100100101000001010011 O
#220000
0+
0`
b100010 -
0i
0g
b1 p
#225000
1+
1`
b1 o
17
06
0k
b0 l
1k
b100 l
02
#226000
b1 Q
b110011001101000100001100111010001000000011011000100000010100100101000001010011001000000010110100111110001000000011010000100000010100100101000001010011 R
b10000 9
b1 K
b100 I
b11000 L
b0 M
b0 N
b11001000110100010000110011101000100000001101000010000001010010010100000101001100100000001011010011111000100000010011110101010101010100 O
#230000
0+
0`
b11000 -
0h
1f
1e
0d
b0 n
b0 p
#235000
1+
1`
b0 m
b0 o
07
05
0k
b0 l
0/
01
#236000
b0 P
b0 Q
b11001000110100010000110011101000100000001101000010000001010010010100000101001100100000001011010011111000100000010011110101010101010100 R
b10001 9
b0 F
b0 H
0G
b0 J
b0 K
b0 I
b0 S
b0 T
b1111 U
#240000
0+
0`
b1111 -
1i
1h
1g
0e
#241000
b0 >
b1111 ?
b0 =
b0 V
b0 A
b0 B
b1111 C
b0 D
b0 @
b0 W
#245000
1+
1`
#246000
b10010 9
b100011 U
#250000
0+
0`
b100011 -
0g
0f
1d
#251000
b100011 ?
b100011 C
#255000
1+
1`
#256000
b10011 9
b1110 U
#260000
0+
0`
b1110 -
0i
1g
1f
0d
b10 n
#261000
b1110 ?
b10 =
b10 V
b1110 C
b0 =
b10 =
b10 D
#265000
1+
1`
b10 m
14
1j
1.
#266000
b10100 9
b10 F
1E
b10 H
b10 J
b100100 U
#270000
0+
0`
b100100 -
b0 m
04
0h
0f
1d
b0 n
b1 n
0j
0.
b1 p
#271000
b100100 ?
b0 =
b1 =
b1 V
b100100 C
b0 =
b1 =
b1 D
b1 @
b1 W
#275000
1+
1`
b1 m
b1 o
17
15
1k
b100 l
1/
11
#276000
b10101 9
b1 F
0E
b1 H
1G
b1 J
b1 K
b100 I
b1 S
b1 T
b11001 U
#280000
0+
0`
b11001 -
1i
0g
1f
1e
0d
#281000
b1 >
b11001 ?
b1 A
b1 B
b11001 C
#285000
1+
1`
#286000
b10110 9
b11000 U
#290000
0+
0`
b11000 -
0i
b0 n
b0 p
#291000
b11000 ?
b0 =
b0 V
b11000 C
b1 =
b0 =
b0 D
b0 @
b0 W
#295000
1+
1`
b0 m
b0 o
07
05
0k
b0 l
0/
01
#296000
b10111 9
b0 F
b0 H
0G
b0 J
b0 K
b0 I
b10 S
b0 T
b11110 U
#300000
0+
0`
b11110 -
b10 m
14
1h
1g
b10 n
1j
1.
#301000
b10 >
b11110 ?
b10 =
b10 V
b10 A
b0 B
b11110 C
b10 D
#305000
1+
1`
#306000
b11000 9
b10 F
1E
b10 H
b10 J
b11111 U
#310000
0+
0`
b11111 -
1i
b0 n
#311000
b11111 ?
b0 =
b0 V
b11111 C
b10 =
b0 =
b0 D
#315000
1+
1`
b0 m
04
0j
0.
#316000
b11001 9
b0 F
0E
b0 H
b0 J
b1 S
b100011 U
#320000
0+
0`
b100011 -
b1 m
15
0g
0f
0e
1d
b1 n
1k
1/
#321000
b1 >
b100011 ?
b1 =
b1 V
b1 A
b100011 C
b1 D
#325000
1+
1`
#326000
b11010 9
b1 F
b1 H
1G
b1 J
b100100 U
#330000
0+
0`
b100100 -
0i
0h
1g
b1 p
#331000
b100100 ?
b100100 C
b1 @
b1 W
#335000
1+
1`
b1 o
17
0k
1k
b100 l
11
